cowpox/Cowpox.py
cowpox/Cowpox_servant.py
cowpox/__init__.py
cowpox/android.py
cowpox/arch.py
cowpox/blacklist.txt
cowpox/bundle.py
cowpox/container.py
cowpox/egg.py
cowpox/graph.py
cowpox/make.py
cowpox/mirror.py
cowpox/platform.py
cowpox/private.py
cowpox/pyrecipe.py
cowpox/recipe.py
cowpox/util.py
cowpox/bootstraps/__init__.py
cowpox/etc/Cowpox.arid
cowpox/etc/__init__.py
cowpox/etc/pyven.arid
cowpox/recipes/__init__.py
cowpox/recipes/android.py
cowpox/recipes/bdozlib.py
cowpox/recipes/cython.py
cowpox/recipes/genericndkbuild.py
cowpox/recipes/kivy.py
cowpox/recipes/libffi.py
cowpox/recipes/numpy.py
cowpox/recipes/openssl.py
cowpox/recipes/pyjnius.py
cowpox/recipes/python3.py
cowpox/recipes/sdl2.py
cowpox/recipes/setuptools.py
cowpox/recipes/six.py
cowpox/recipes/sqlite3/__init__.py
cowpox/recipes/sqlite3/jni/Android.mk
cowpox/recipes/sqlite3/jni/__init__.py
Cowpox-6.dist-info/COPYING
Cowpox-6.dist-info/LICENSE.kivy
Cowpox-6.dist-info/METADATA
Cowpox-6.dist-info/WHEEL
Cowpox-6.dist-info/entry_points.txt
Cowpox-6.dist-info/top_level.txt
Cowpox-6.dist-info/RECORD
