Metadata-Version: 2.1
Name: Cowpox
Version: 6
Summary: Deploy Android apps written in Python
Home-page: https://github.com/combatopera/Cowpox
Author: Andrzej Cichocki
License: UNKNOWN
Platform: UNKNOWN
License-File: LICENSE.kivy
License-File: COPYING
Requires-Dist: aridity (>=45)
Requires-Dist: chromalog (>=1.0.4)
Requires-Dist: Cython (>=0.29.20)
Requires-Dist: diapyr (>=18)
Requires-Dist: jproperties (>=2.1.0)
Requires-Dist: lagoon (>=22)
Requires-Dist: networkx (>=2.4)
Requires-Dist: packaging (>=20.4)
Requires-Dist: setuptools (>=44.1.1)
